pytrading212/__init__.py
pytrading212/console.py
pytrading212/constants.py
pytrading212/instrument.py
pytrading212/order.py
pytrading212/position.py
pytrading212/trading212.py
pytrading212/utils.py
pytrading212-0.2.8.dist-info/LICENSE
pytrading212-0.2.8.dist-info/METADATA
pytrading212-0.2.8.dist-info/WHEEL
pytrading212-0.2.8.dist-info/RECORD
