Metadata-Version: 2.1
Name: pytrading212
Version: 0.2.8
Summary: Unofficial Trading212 API
License: MIT
Author: HellAmbro
Author-email: frambrosini1998@gmail.com
Requires-Python: >=3.7,<4.0
Classifier: License :: OSI Approved :: MIT License
Classifier: Programming Language :: Python :: 3
Classifier: Programming Language :: Python :: 3.7
Classifier: Programming Language :: Python :: 3.8
Classifier: Programming Language :: Python :: 3.9
Classifier: Programming Language :: Python :: 3.10
Classifier: Programming Language :: Python :: 3.11
Classifier: Programming Language :: Python :: 3.12
Requires-Dist: requests (>=2.28.2,<3.0.0)
Requires-Dist: rich (>=13.3.2,<14.0.0)
Requires-Dist: selenium (>=4.8.2,<5.0.0)
Requires-Dist: webdriver-manager (>=3.8.5,<4.0.0)
